neurons/__init__.py
neurons/api.py
neurons/miner.py
neurons/validator.py
storage/__init__.py
storage/constants.py
storage/protocol.py
storage/api/__init__.py
storage/api/base.py
storage/api/delete_api.py
storage/api/example.py
storage/api/retrieve_api.py
storage/api/store_api.py
storage/api/utils.py
storage/cli/__init__.py
storage/cli/cli.py
storage/cli/default_values.py
storage/cli/listcommand.py
storage/cli/neuroncommand.py
storage/cli/retrievecommand.py
storage/cli/statscommand.py
storage/cli/storecommand.py
storage/indexer/__init__.py
storage/indexer/endpoint.py
storage/indexer/redis.py
storage/indexer/sqlite.py
storage/miner/__init__.py
storage/miner/config.py
storage/miner/database.py
storage/miner/run.py
storage/miner/set_weights.py
storage/miner/utils.py
storage/plot/__init__.py
storage/plot/utils.py
storage/shared/__init__.py
storage/shared/checks.py
storage/shared/ecc.py
storage/shared/merkle.py
storage/shared/subtensor.py
storage/shared/utils.py
storage/shared/weights.py
storage/validator/__init__.py
storage/validator/bonding.py
storage/validator/challenge.py
storage/validator/cid.py
storage/validator/config.py
storage/validator/database.py
storage/validator/dendrite.py
storage/validator/distribute.py
storage/validator/encryption.py
storage/validator/event.py
storage/validator/forward.py
storage/validator/network.py
storage/validator/rebalance.py
storage/validator/retrieve.py
storage/validator/reward.py
storage/validator/state.py
storage/validator/store.py
storage/validator/utils.py
storage/validator/verify.py
storage/validator/weights.py
tests/__init__.py
tests/integration/__init__.py
tests/unit/__init__.py
tests/unit/cli/__init__.py
tests/unit/cli/test_cli.py
tests/unit/cli/test_neuroncommand.py
tests/unit/validator/__init__.py
tests/unit/validator/test_challenge.py
tests/unit/validator/test_encryption.py
tests/unit/validator/test_state.py
FileTAO-3.0.2.dist-info/LICENSE
FileTAO-3.0.2.dist-info/METADATA
FileTAO-3.0.2.dist-info/WHEEL
FileTAO-3.0.2.dist-info/entry_points.txt
FileTAO-3.0.2.dist-info/top_level.txt
FileTAO-3.0.2.dist-info/RECORD
