Metadata-Version: 2.1
Name: FileTAO
Version: 3.0.2
Summary: Philanthropic storage for the masses. (FileTAO)
Home-page: https://github.com/ifrit98/storage-subnet
Author: philanthrope
Author-email: ifrit98@gmail.com
License: MIT
Classifier: Development Status :: 3 - Alpha
Classifier: Intended Audience :: Developers
Classifier: Topic :: Software Development :: Build Tools
Classifier: License :: OSI Approved :: MIT License
Classifier: Programming Language :: Python :: 3 :: Only
Classifier: Programming Language :: Python :: 3.9
Classifier: Programming Language :: Python :: 3.10
Classifier: Programming Language :: Python :: 3.11
Classifier: Topic :: Scientific/Engineering
Classifier: Topic :: Scientific/Engineering :: Mathematics
Classifier: Topic :: Scientific/Engineering :: Artificial Intelligence
Classifier: Topic :: Software Development
Classifier: Topic :: Software Development :: Libraries
Classifier: Topic :: Software Development :: Libraries :: Python Modules
Requires-Python: >=3.9,<3.12
License-File: LICENSE
Requires-Dist: torch >=1.13.0
Requires-Dist: bcrypt ==3.2.0
Requires-Dist: bittensor ==6.12.2
Requires-Dist: redis ==5.0.1
Requires-Dist: pycryptodome ==3.20.0
Requires-Dist: pyinstrument ==4.6.1
Requires-Dist: wandb ==0.16.0
Requires-Dist: morphys ==1.0
Requires-Dist: py-multibase ==1.0.3
Requires-Dist: py-multicodec ==0.2.1
Requires-Dist: py-multihash ==2.0.1
Requires-Dist: ipfs-cid ==1.0.0
Requires-Dist: pyjwt >=2.8.0
Requires-Dist: passlib ==1.7.4
Requires-Dist: python-multipart ==0.0.9
Requires-Dist: python-dotenv ==1.0.1
Requires-Dist: loguru ==0.7.0
Requires-Dist: pandas ==2.2.0
Provides-Extra: dev
Requires-Dist: pytest ==7.4.3 ; extra == 'dev'
Requires-Dist: pytest-cov ==4.1.0 ; extra == 'dev'
Requires-Dist: parameterized ==0.9.0 ; extra == 'dev'
Requires-Dist: flake8 ==7.0.0 ; extra == 'dev'
